SecureAgent/__init__.py
SecureAgent/cache.py
SecureAgent/cli.py
SecureAgent/core.py
SecureAgent/exceptions.py
SecureAgent/exchange.py
SecureAgent/registration.py
secureagent-0.1.3.dist-info/METADATA
secureagent-0.1.3.dist-info/WHEEL
secureagent-0.1.3.dist-info/entry_points.txt
secureagent-0.1.3.dist-info/licenses/LICENSE.md
secureagent-0.1.3.dist-info/RECORD
