Metadata-Version: 2.4
Name: SecureAgent
Version: 0.1.3
Summary: Agentic Identity Framework abstracting Keycloak/OIDC complexity for AI Agents
Author-email: Sam Armstrong <DO_NOT_EMAIL_USE_ISSUES@github.com>
License-Expression: MIT
License-File: LICENSE.md
Keywords: agents,ai,keycloak,oidc,security
Requires-Python: >=3.10
Requires-Dist: click>=8.0
Requires-Dist: fastapi
Requires-Dist: httpx
Requires-Dist: pydantic
Requires-Dist: python-keycloak
Provides-Extra: test
Requires-Dist: httpx; extra == 'test'
Requires-Dist: pytest; extra == 'test'
Requires-Dist: pytest-asyncio; extra == 'test'
Requires-Dist: pytest-cov; extra == 'test'
Requires-Dist: pytest-mock; extra == 'test'
Requires-Dist: python-keycloak; extra == 'test'
